ckanext/__init__.py
ckanext/harvest_basket/__init__.py
ckanext/harvest_basket/plugin.py
ckanext/harvest_basket/action/__init__.py
ckanext/harvest_basket/action/auth/__init__.py
ckanext/harvest_basket/action/auth/get.py
ckanext/harvest_basket/action/logic/__init__.py
ckanext/harvest_basket/action/logic/get.py
ckanext/harvest_basket/assets/webassets.yml
ckanext/harvest_basket/assets/css/harvest_basket.css
ckanext/harvest_basket/assets/js/harvest_basket.js
ckanext/harvest_basket/harvesters/__init__.py
ckanext/harvest_basket/harvesters/arcgis_harvester.py
ckanext/harvest_basket/harvesters/base_harvester.py
ckanext/harvest_basket/harvesters/ckan_harvester.py
ckanext/harvest_basket/harvesters/csiro.py
ckanext/harvest_basket/harvesters/csw.py
ckanext/harvest_basket/harvesters/dcat.py
ckanext/harvest_basket/harvesters/dkan_harvester.py
ckanext/harvest_basket/harvesters/junar_harvester.py
ckanext/harvest_basket/harvesters/ods_harvester.py
ckanext/harvest_basket/harvesters/socrata_harvester.py
ckanext/harvest_basket/templates/base.html
ckanext/harvest_basket/templates/source/new_source_form.html
ckanext/harvest_basket/tests/__init__.py
ckanext/harvest_basket/tests/test_plugin.py
ckanext_harvest_basket-1.3.73.dist-info/LICENSE
ckanext_harvest_basket-1.3.73.dist-info/METADATA
ckanext_harvest_basket-1.3.73.dist-info/WHEEL
ckanext_harvest_basket-1.3.73.dist-info/entry_points.txt
ckanext_harvest_basket-1.3.73.dist-info/top_level.txt
ckanext_harvest_basket-1.3.73.dist-info/RECORD
